<?xml version="1.0" encoding="UTF-8" standalone="yes" ?>
<quizz fournisseur="OpenQuizzDB : Fournisseur de contenu libre"
       url="https://www.openquizzdb.org"
       rédacteur="Philippe Bresoux"
       thème="X-Files : la série (Aux frontières du réel)"
       difficulté="3 / 5">
  <fr>
  <débutant>
    <contenu id="1">
      <question>Dans quel service de renseignement intérieur travaillent les agents Mulder et Scully ?</question>
      <propositions>
        <proposition id="1-1">CSI</proposition>
        <proposition id="1-2">FBI</proposition>
        <proposition id="1-3">CIA</proposition>
        <proposition id="1-4">NSA</proposition>
      </propositions>
      <réponse proposition="1-2">FBI</réponse>
      <anecdote>Les attributions du FBI incluent l'antiterrorisme, le contre-espionnage, le crime informatique et la médecine légale.</anecdote>
    </contenu>
    <contenu id="2">
      <question>Qui est le supérieur hiérarchique direct de Mulder et Scully dans la série « X-Files » ?</question>
      <propositions>
        <proposition id="2-1">Wallace Sommer</proposition>
        <proposition id="2-2">Chris Carter</proposition>
        <proposition id="2-3">Walter Skinner</proposition>
        <proposition id="2-4">William Stabler</proposition>
      </propositions>
      <réponse proposition="2-3">Walter Skinner</réponse>
      <anecdote>Walter Skinner est un ancien marine qui a fait le Vietnam et en cela il est sévère, exigeant mais toutefois juste et honnête.</anecdote>
    </contenu>
    <contenu id="3">
      <question>Qu'y a-t-il d'écrit sur la célèbre affiche qui se trouve dans le bureau de Fox Mulder ?</question>
      <propositions>
        <proposition id="3-1">Do aliens exist  ?</proposition>
        <proposition id="3-2">Are you scared  ?</proposition>
        <proposition id="3-3">U.F.O.</proposition>
        <proposition id="3-4">I want to believe</proposition>
      </propositions>
      <réponse proposition="3-4">I want to believe</réponse>
      <anecdote>Intuitif et paranoïaque, Mulder est considéré comme étrange et excentrique par ses pairs, ce qui lui a valu le surnom de « Martien ».</anecdote>
    </contenu>
    <contenu id="4">
      <question>Durant quelle saison apparaît pour la première fois l'homme à la cigarette dans « X-Files » ?</question>
      <propositions>
        <proposition id="4-1">Saison 1</proposition>
        <proposition id="4-2">Saison 4</proposition>
        <proposition id="4-3">Saison 3</proposition>
        <proposition id="4-4">Saison 2</proposition>
      </propositions>
      <réponse proposition="4-1">Saison 1</réponse>
      <anecdote>De nature froide et solitaire à l'origine, la série le fait évoluer pour faire comprendre qu'il est le personnage incontournable du complot.</anecdote>
    </contenu>
    <contenu id="5">
      <question>Quelle était la profession de Scully avant de devenir agent du FBI dans « X-Files » ?</question>
      <propositions>
        <proposition id="5-1">Photographe</proposition>
        <proposition id="5-2">Avocate</proposition>
        <proposition id="5-3">Médecin</proposition>
        <proposition id="5-4">Architecte</proposition>
      </propositions>
      <réponse proposition="5-3">Médecin</réponse>
      <anecdote>Scully a échappé à de nombreuses reprises à la mort durant la série, et au moins 2 épisodes laissent penser qu'elle serait immortelle.</anecdote>
    </contenu>
    <contenu id="6">
      <question>Combien de saisons compte la série télévisée « X-Files : Aux frontières du réel » ?</question>
      <propositions>
        <proposition id="6-1">Diz</proposition>
        <proposition id="6-2">Huit</proposition>
        <proposition id="6-3">Onze</proposition>
        <proposition id="6-4">Neuf</proposition>
      </propositions>
      <réponse proposition="6-3">Onze</réponse>
      <anecdote>La série décrit les différentes enquêtes des agents spéciaux du FBI Fox Mulder et Dana Scully sur des dossiers classés X (X-Files).</anecdote>
    </contenu>
    <contenu id="7">
      <question>Quelle actrice interprète le rôle de Dana Scully dans la série télé « X-Files » ?</question>
      <propositions>
        <proposition id="7-1">Gillian Anderson</proposition>
        <proposition id="7-2">Annabeth Gish</proposition>
        <proposition id="7-3">Jolie Jenkins</proposition>
        <proposition id="7-4">Laurie Holden</proposition>
      </propositions>
      <réponse proposition="7-1">Gillian Anderson</réponse>
      <anecdote>Gillian Anderson a été récompensée pour ce rôle par un Golden Globes Award et un Primetime Emmy Award.</anecdote>
    </contenu>
    <contenu id="8">
      <question>Quel est le surnom donné à Fox Mulder par ses collègues dans la série télé « X-Files » ?</question>
      <propositions>
        <proposition id="8-1">Martien</proposition>
        <proposition id="8-2">Bibou</proposition>
        <proposition id="8-3">Biquet</proposition>
        <proposition id="8-4">Matrix</proposition>
      </propositions>
      <réponse proposition="8-1">Martien</réponse>
      <anecdote>Mulder est le nom de jeune fille de la mère de Chris Carter, réalisateur de la série, et Fox est le nom de l'un de ses amis.</anecdote>
    </contenu>
    <contenu id="9">
      <question>Quel acteur remplace David Duchovny dans les saisons 6, 7 et 8 de « X-Files » ?</question>
      <propositions>
        <proposition id="9-1">Robert Pattinson</proposition>
        <proposition id="9-2">Robert Patrick</proposition>
        <proposition id="9-3">Robert Downey Jr.</proposition>
        <proposition id="9-4">Robert Wagner</proposition>
      </propositions>
      <réponse proposition="9-2">Robert Patrick</réponse>
      <anecdote>Robert Patrick a été révélé au cinéma en 1991 par son interprétation du T-1000 dans le second volet de la saga « Terminator ».</anecdote>
    </contenu>
    <contenu id="10">
      <question>Quel scénariste, réalisateur et producteur américain a créé la série télévisée « X-Files » ?</question>
      <propositions>
        <proposition id="10-1">Chris Carter</proposition>
        <proposition id="10-2">J.J. Abrams</proposition>
        <proposition id="10-3">Steven Spielberg</proposition>
        <proposition id="10-4">Guillermo del Toro</proposition>
      </propositions>
      <réponse proposition="10-1">Chris Carter</réponse>
      <anecdote>Chris Carter a reçu en 1999 le PGA Award du producteur de télévision le plus prometteur.</anecdote>
    </contenu>
  </débutant>
  <confirmé>
    <contenu id="11">
      <question>Dans quelle ville des États-Unis se trouve le bureau de Mulder et Scully ?</question>
      <propositions>
        <proposition id="11-1">Dallas</proposition>
        <proposition id="11-2">Washington</proposition>
        <proposition id="11-3">New York</proposition>
        <proposition id="11-4">Los Angeles</proposition>
      </propositions>
      <réponse proposition="11-2">Washington</réponse>
      <anecdote>Fox Mulder est un homme qui voue une véritable passion à tout ce qui touche au paranormal.</anecdote>
    </contenu>
    <contenu id="12">
      <question>Quelle aventurière de fiction a fait une apparition remarquée dans la série « X-Files » ?</question>
      <propositions>
        <proposition id="12-1">Super Jamie</proposition>
        <proposition id="12-2">Xena</proposition>
        <proposition id="12-3">Buffy</proposition>
        <proposition id="12-4">Lara Croft</proposition>
      </propositions>
      <réponse proposition="12-2">Xena</réponse>
      <anecdote>En 1995, avant de devenir Xena, Lucy Lawless fut le personnage central de « Peach », un court-métrage traitant de l'homosexualité.</anecdote>
    </contenu>
    <contenu id="13">
      <question>Dans « X-Files », quel meurtrier abolit les foies de ses victimes ?</question>
      <propositions>
        <proposition id="13-1">Hosteen</proposition>
        <proposition id="13-2">Krycek</proposition>
        <proposition id="13-3">Tooms</proposition>
        <proposition id="13-4">Burks</proposition>
      </propositions>
      <réponse proposition="13-3">Tooms</réponse>
      <anecdote>Tous les 30 ans, Eugène Victor Tooms sort de son hibernation pour se nourrir du foie d'êtres humains.</anecdote>
    </contenu>
    <contenu id="14">
      <question>Quel est le prénom de la soeur disparue de Fox Mulder dans la série « X-Files » ?</question>
      <propositions>
        <proposition id="14-1">Joanna</proposition>
        <proposition id="14-2">Samantha</proposition>
        <proposition id="14-3">Rita</proposition>
        <proposition id="14-4">Alicia</proposition>
      </propositions>
      <réponse proposition="14-2">Samantha</réponse>
      <anecdote>Samantha Ann Mulder, née le 22 janvier 1964, est disparue le 27 novembre 1973 (Affaire non classée : dossier n° X-42053).</anecdote>
    </contenu>
    <contenu id="15">
      <question>Combien de films ont été tirés de la série télévisée « X-Files » ?</question>
      <propositions>
        <proposition id="15-1">2</proposition>
        <proposition id="15-2">3</proposition>
        <proposition id="15-3">Aucun</proposition>
        <proposition id="15-4">1</proposition>
      </propositions>
      <réponse proposition="15-1">2</réponse>
      <anecdote>Les deux films sont « The X-Files, le film » de Rob S. Bowman, sorti en 1998, et « X-Files : Régénération » de Chris Carter, sorti en 2008.</anecdote>
    </contenu>
    <contenu id="16">
      <question>Qui est le père de l'enfant de Scully dans la série télévisée « X-Files » ?</question>
      <propositions>
        <proposition id="16-1">Mulder</proposition>
        <proposition id="16-2">Doggett</proposition>
        <proposition id="16-3">Krycek</proposition>
        <proposition id="16-4">Skinner</proposition>
      </propositions>
      <réponse proposition="16-1">Mulder</réponse>
      <anecdote>Scully a une vie sentimentale et sociale assez terne, se retranchant le plus souvent dans ses expériences scientifiques et ses recherches.</anecdote>
    </contenu>
    <contenu id="17">
      <question>Quel personnage de la série « X-Files » a perdu un bras suite à l'inoculation d'un vaccin ?</question>
      <propositions>
        <proposition id="17-1">Krycek</proposition>
        <proposition id="17-2">Monsieur X</proposition>
        <proposition id="17-3">Pendrell</proposition>
        <proposition id="17-4">Skinner</proposition>
      </propositions>
      <réponse proposition="17-1">Krycek</réponse>
      <anecdote>Présenté comme un partenaire mais perçu comme un élément gênant par l'agent Fox Mulder, Alex Krycek s'avère être un traître.</anecdote>
    </contenu>
    <contenu id="18">
      <question>De quelle maladie souffre Scully à partir de la saison 4 de la série « X-Files » ?</question>
      <propositions>
        <proposition id="18-1">Diabète</proposition>
        <proposition id="18-2">Amnésie</proposition>
        <proposition id="18-3">Sclérose</proposition>
        <proposition id="18-4">Cancer</proposition>
      </propositions>
      <réponse proposition="18-4">Cancer</réponse>
      <anecdote>Scully a mis en doute ses croyances lorsqu'on lui diagnostiqua un cancer du cerveau, conséquence de son enlèvement.</anecdote>
    </contenu>
    <contenu id="19">
      <question>Quel est le nom du chien de Dana Scully de la série « X-Files » ?</question>
      <propositions>
        <proposition id="19-1">Gish</proposition>
        <proposition id="19-2">Fox</proposition>
        <proposition id="19-3">Bobby</proposition>
        <proposition id="19-4">Queequeg</proposition>
      </propositions>
      <réponse proposition="19-4">Queequeg</réponse>
      <anecdote>Plus jeune, le livre préféré de Dana Scully était « Moby Dick », que son père prenait plaisir à lui lire très souvent.</anecdote>
    </contenu>
    <contenu id="20">
      <question>Dans « X-Files », quel membre du FBI est mort dans les bras de Scully ?</question>
      <propositions>
        <proposition id="20-1">Scott Blevins</proposition>
        <proposition id="20-2">Monica Reyes</proposition>
        <proposition id="20-3">Jeffrey Spender</proposition>
        <proposition id="20-4">Agent Pendrell</proposition>
      </propositions>
      <réponse proposition="20-4">Agent Pendrell</réponse>
      <anecdote>L'agent Pendrell est un membre du laboratoire en sciences criminelles du FBI, qui assiste occasionnellement l'agent Dana Scully.</anecdote>
    </contenu>
  </confirmé>
  <expert>
    <contenu id="21">
      <question>Comment se surnomment les trois amis paranoïaques de Mulder dans « X-Files » ?</question>
      <propositions>
        <proposition id="21-1">Lone Cowboys</proposition>
        <proposition id="21-2">Lone Gunmen</proposition>
        <proposition id="21-3">Lone Rangers</proposition>
        <proposition id="21-4">Lone Stars</proposition>
      </propositions>
      <réponse proposition="21-2">Lone Gunmen</réponse>
      <anecdote>Ce trio est l'alliance improbable d'un bidouilleur en électronique, d'un pirate informatique et d'un ex-salarié des télécommunications.</anecdote>
    </contenu>
    <contenu id="22">
      <question>Quel est le titre du dernier épisode de la série télévisée « X-Files » ?</question>
      <propositions>
        <proposition id="22-1">La vérité est ici</proposition>
        <proposition id="22-2">La découverte</proposition>
        <proposition id="22-3">La Prophétie</proposition>
        <proposition id="22-4">La soif de savoir</proposition>
      </propositions>
      <réponse proposition="22-1">La vérité est ici</réponse>
      <anecdote>Dans cet ultime épisode, la date de l'invasion coïncide avec le calendrier maya et les prédictions pour décembre 2012.</anecdote>
    </contenu>
    <contenu id="23">
      <question>Quelle est le prénom de la fille de Scully dans la série « X-Files » ?</question>
      <propositions>
        <proposition id="23-1">Janis</proposition>
        <proposition id="23-2">Diane</proposition>
        <proposition id="23-3">Emily</proposition>
        <proposition id="23-4">Emma</proposition>
      </propositions>
      <réponse proposition="23-3">Emily</réponse>
      <anecdote>Interprétée par Lauren Diewold, cette petite fille (Emily Sim) apparaît dans le double épisode « Emily » de la saison 5 de la série.</anecdote>
    </contenu>
    <contenu id="24">
      <question>De quelle université Mulder, de la série « X-Files », est-il diplômé ?</question>
      <propositions>
        <proposition id="24-1">Yale</proposition>
        <proposition id="24-2">Manchester</proposition>
        <proposition id="24-3">Princeton</proposition>
        <proposition id="24-4">Oxford</proposition>
      </propositions>
      <réponse proposition="24-4">Oxford</réponse>
      <anecdote>De 1983 à 1986, Fox Mulder étudie à Oxford en Angleterre et sort premier de sa promotion avec en poche son diplôme en psychologie.</anecdote>
    </contenu>
    <contenu id="25">
      <question>Quelle actrice remplace Gillian Anderson dans les dernières saisons de la série « X-Files » ?</question>
      <propositions>
        <proposition id="25-1">Annabella Sciorra</proposition>
        <proposition id="25-2">Anna Faris</proposition>
        <proposition id="25-3">Annabeth Gish</proposition>
        <proposition id="25-4">Jolie Jenkins</proposition>
      </propositions>
      <réponse proposition="25-3">Annabeth Gish</réponse>
      <anecdote>Elle est nommée pour ce rôle au Saturn Award de la meilleure actrice de télévision dans un second rôle en 2002.</anecdote>
    </contenu>
    <contenu id="26">
      <question>Qui enlève Scully pour la remettre aux aliens dans la saison 2 de « X-Files » ?</question>
      <propositions>
        <proposition id="26-1">Brad Follmer</proposition>
        <proposition id="26-2">Chuck Burks</proposition>
        <proposition id="26-3">Billy Miles</proposition>
        <proposition id="26-4">Duane Barry</proposition>
      </propositions>
      <réponse proposition="26-4">Duane Barry</réponse>
      <anecdote>Dans l'épisode en question, c'est l'acteur lui-même qui a réalisé la cascade sur le toit du téléphérique, mettant sa propre vie en danger.</anecdote>
    </contenu>
    <contenu id="27">
      <question>Quel est le mot de passe de l'ordinateur de Mulder dans la série « X-Files » ?</question>
      <propositions>
        <proposition id="27-1">Aliens</proposition>
        <proposition id="27-2">Trustno1</proposition>
        <proposition id="27-3">Scully</proposition>
        <proposition id="27-4">Samantha</proposition>
      </propositions>
      <réponse proposition="27-2">Trustno1</réponse>
      <anecdote>Fox Mulder possède peu d'amis mais un bon nombre de contacts, ce qui lui est très utile durant l'ensemble de la série.</anecdote>
    </contenu>
    <contenu id="28">
      <question>Quelle marque de cigarettes fume l'homme à la cigarette dans la série « X-Files » ?</question>
      <propositions>
        <proposition id="28-1">Mighton</proposition>
        <proposition id="28-2">Morley</proposition>
        <proposition id="28-3">On ne sait pas</proposition>
        <proposition id="28-4">Marlac</proposition>
      </propositions>
      <réponse proposition="28-2">Morley</réponse>
      <anecdote>Cette marque est apparue dans divers autres films de télévision et de cinéma, séries télévisées et jeux vidéo.</anecdote>
    </contenu>
    <contenu id="29">
      <question>Quel surnom a été donné à Scully par son père dans la série télévisée « X-Files » ?</question>
      <propositions>
        <proposition id="29-1">Queequeg</proposition>
        <proposition id="29-2">Janis</proposition>
        <proposition id="29-3">La martienne</proposition>
        <proposition id="29-4">Starbuck</proposition>
      </propositions>
      <réponse proposition="29-4">Starbuck</réponse>
      <anecdote>Fan du roman « Moby Dick », il la surnommait « Starbuck » et Scully l'appelait en retour « Achab ».</anecdote>
    </contenu>
    <contenu id="30">
      <question>Quel épisode de « X-Files » diffusé en 1999 se répète à l'infini ?</question>
      <propositions>
        <proposition id="30-1">Jour J</proposition>
        <proposition id="30-2">Pour toujours</proposition>
        <proposition id="30-3">Lundi</proposition>
        <proposition id="30-4">Réitération</proposition>
      </propositions>
      <réponse proposition="30-3">Lundi</réponse>
      <anecdote>Pris dans une boucle temporelle, Mulder doit empêcher une bombe d'exploser dans une banque pour y mettre fin.</anecdote>
    </contenu>
  </expert>
  </fr>
</quizz>