{
  "fournisseur": "OpenQuizzDB - Fournisseur de contenu libre (www.openquizzdb.org)",
  "rédacteur": "Philippe Bresoux",
  "thème": "Actu people : mars 2018",
  "difficulté": 2,
  "quizz": {
    "débutant": [
      {
        "id": 1,
        "question": "Quel compositeur français a reçu un second Oscar pour 'La Forme de l'eau' ?",
        "propositions": [
          "Alexandre Desplat",
          "Olivier Florio",
          "Michel Legrand",
          "Francis Lai"
        ],
        "réponse": "Alexandre Desplat",
        "anecdote": "Trois ans après 'The Grand Budapest Hotel', le compositeur français Alexandre Desplat triomphe à nouveau aux Oscars."
      },
      {
        "id": 2,
        "question": "Quel présentateur star de RMC est aussi intervieweur politique sur BFM TV ?",
        "propositions": [
          "Jean-Jacques Bourdin",
          "Philippe Verdier",
          "Bruno Masure",
          "Patrick Sabatier"
        ],
        "réponse": "Jean-Jacques Bourdin",
        "anecdote": "À 68 ans, avec sa voix reconnaissable entre toutes, il incarne un style de journalisme pugnace souvent taxé de populisme."
      },
      {
        "id": 3,
        "question": "Qui fut contrainte début 2018 d'annuler des concerts faute de public ?",
        "propositions": [
          "Alizée",
          "Enzo Enzo",
          "Shy'm",
          "Anggun"
        ],
        "réponse": "Shy'm",
        "anecdote": "Shy'm s'est exprimée sur l'échec de sa dernière tournée pour laquelle elle n'a eu d'autre choix que d'annuler plusieurs concerts."
      },
      {
        "id": 4,
        "question": "Qui fut le manager attitré de JoeyStarr pendant près de 25 ans ?",
        "propositions": [
          "Sébastien Farran",
          "Jimmy Jay",
          "DJ Abdel",
          "Doctor Flake"
        ],
        "réponse": "Sébastien Farran",
        "anecdote": "Leur rupture ne s'est pas faite en douceur et le rappeur ne manque jamais une occasion de dire le mal qu'il pense de son ancien acolyte."
      },
      {
        "id": 5,
        "question": "Qui a rendu un vibrant hommage à Jeanne Moreau aux César 2018 ?",
        "propositions": [
          "Sandrine Kiberlain",
          "Géraldine Pailhas",
          "Vanessa Paradis",
          "Romane Bohringer"
        ],
        "réponse": "Vanessa Paradis",
        "anecdote": "Vanessa Paradis et Jeanne Moreau avaient jadis signé ensemble un des plus jolis moments de l'histoire du Festival, en 1995."
      },
      {
        "id": 6,
        "question": "Quelle ancienne chroniqueuse de l'émission 'TPMP' souffre d'endométriose ?",
        "propositions": [
          "Énora Malagré",
          "Kelly Vedovelli",
          "Agathe Auproux",
          "Valérie Bénaïm"
        ],
        "réponse": "Énora Malagré",
        "anecdote": "Énora Malagré a confié sur Europe 1 avoir participé à un documentaire sur Teva pour lever le tabou sur cette maladie."
      },
      {
        "id": 7,
        "question": "Qui est apparue très amincie sur la couverture du magazine 'Elle' ?",
        "propositions": [
          "Afida Turner",
          "Loana Petrucciani",
          "Kenza Braiga",
          "Julie Bouville"
        ],
        "réponse": "Loana Petrucciani",
        "anecdote": "Sa silhouette a beaucoup souffert de sa descente aux enfers, si bien qu'avec cette couverture, certains crient « Photoshop »."
      },
      {
        "id": 8,
        "question": "Qui a dû se faire baptiser avant de pouvoir prétendre à se marier ?",
        "propositions": [
          "Meghan Markle",
          "Gina Torres",
          "Katherine Heigl",
          "Sarah Rafferty"
        ],
        "réponse": "Meghan Markle",
        "anecdote": "Meghan Markle s'est fait baptiser le 6 mars selon les rites de l'Église Anglicane, au préalable à son mariage avec Harry le 19 mai."
      },
      {
        "id": 9,
        "question": "Quel astrophysicien et vulgarisateur scientifique est mort à l'âge de 76 ans ?",
        "propositions": [
          "Stephen Hawking",
          "Paul Steinhardt",
          "Edward Kolb",
          "John Bahcall"
        ],
        "réponse": "Stephen Hawking",
        "anecdote": "Au fil d'une carrière très dense, Stephen Hawking a su devenir aussi une icône pop à travers différentes apparitions dans des séries télé."
      },
      {
        "id": 10,
        "question": "Qui a été réélue Chancelière d'Allemagne pour la quatrième fois ?",
        "propositions": [
          "Erna Solberg",
          "Hilda Heine",
          "Angela Merkel",
          "Julie Payette"
        ],
        "réponse": "Angela Merkel",
        "anecdote": "C'est historique : après des mois de négociations, la Chancelière allemande Angela Merkel vient d'être réélue à la tête du pays."
      }
    ],
    "confirmé": [
      {
        "id": 11,
        "question": "Quel acteur de la série 'Grey's Anatomy' s'est remarié avec Arielle Goldrath ?",
        "propositions": [
          "Jesse Williams",
          "Kevin McKidd",
          "Justin Chambers",
          "Jason George"
        ],
        "réponse": "Kevin McKidd",
        "anecdote": "Né en Écosse, naturalisé américain en 2015, Kevin McKidd s'est marié en kilt comme il l'a dévoilé en photo le 2 mars 2018."
      },
      {
        "id": 12,
        "question": "Quelle est la valeur du « sac cadeaux » des nommés aux Oscars 2018 ?",
        "propositions": [
          "400 000 dollars",
          "200 000 dollars",
          "100 000 dollars",
          "300 000 dollars"
        ],
        "réponse": "100 000 dollars",
        "anecdote": "Le « swag bag » comprend : séjours en Tanzanie, à Hawaï et en Grèce, spa, coaching, rouge à lèvres, faux-cils et chocolat."
      },
      {
        "id": 13,
        "question": "Aux côtés de qui les Anges 10 ont-ils posé aux Hollywood Beauty Awards ?",
        "propositions": [
          "Britney Spears",
          "Cheryl Cole",
          "Paula Abdul",
          "Nicole Scherzinger"
        ],
        "réponse": "Britney Spears",
        "anecdote": "Une cérémonie lors de laquelle Britney Spears a été récompensée d'un prix d'honneur pour son parfum baptisé Fantasy in Bloom."
      },
      {
        "id": 14,
        "question": "Avec quel acteur Sophie Morceau a-t-elle déclaré avoir échangé son plus beau baiser ?",
        "propositions": [
          "Mel Gibson",
          "Pierce Brosnan",
          "Yvan Attal",
          "Vincent Pérez"
        ],
        "réponse": "Mel Gibson",
        "anecdote": "Du haut de ses 51 ans, l'actrice ne semble pas avoir pris une ride depuis ses premiers pas sur nos écrans dans 'La Boum'."
      },
      {
        "id": 15,
        "question": "Quelle icône de la mode emploie 75% de femmes dans ses sociétés ?",
        "propositions": [
          "Geri Halliwell",
          "Melanie Brown",
          "Victoria Beckham",
          "Emma Bunton"
        ],
        "réponse": "Victoria Beckham",
        "anecdote": "C'est en 1997 que Victoria a rencontré David Beckham alors qu'elle assistait à un match avec son amie Melanie Chisholm."
      },
      {
        "id": 16,
        "question": "Qui Vanessa Paradis a-t-elle dévoré du regard à l'avant-première de 'Chien' ?",
        "propositions": [
          "Alain Berberian",
          "Samuel Benchetrit",
          "Antonin Bideau",
          "Ludovic Bernard"
        ],
        "réponse": "Samuel Benchetrit",
        "anecdote": "La belle très amoureuse n'a pas quitté des yeux son homme avec qui elle partage sa vie depuis 2016 et devrait bientôt se marier."
      },
      {
        "id": 17,
        "question": "Quelle navigatrice a annoncé être bientôt maman pour la quatrième fois ?",
        "propositions": [
          "Maud Fontenoy",
          "Aude Compan",
          "Mathilde Géron",
          "Élodie Bertrand"
        ],
        "réponse": "Maud Fontenoy",
        "anecdote": "La navigatrice française est également vice-présidente déléguée au Développement durable, à l'énergie et à la mer de la région PACA."
      },
      {
        "id": 18,
        "question": "Quel chanteur s'apprête à retourner en studio après un séjour en maison de repos ?",
        "propositions": [
          "Arthur H",
          "Renaud",
          "Bénabar",
          "Daran"
        ],
        "réponse": "Renaud",
        "anecdote": "Cet album sera un peu particulier, puisqu'il s'agit d'un opus de chansons pour enfants toutes signées de la main du chanteur."
      },
      {
        "id": 19,
        "question": "Quel rappeur a fait la couverture de Playboy France, oreilles de lapin sur la tête ?",
        "propositions": [
          "JoeyStarr",
          "MC Solaar",
          "Kool Shen",
          "Booba"
        ],
        "réponse": "JoeyStarr",
        "anecdote": "L'édition française de Playboy, lancée en 1973, a mis en avant des personnalités très diverses au fil des années."
      },
      {
        "id": 20,
        "question": "En pleine promo de son autobiographie intitulée 'Authentique', qui a révélé avoir avorté ?",
        "propositions": [
          "Claudia Romani",
          "Ayem Nour",
          "Marie Sebag",
          "Capucine Anav"
        ],
        "réponse": "Capucine Anav",
        "anecdote": "Capucine Anav a profité de son passage dans l'émission 'Morandini Live', diffusée sur CNews et Non Stop People, pour l'annoncer."
      }
    ],
    "expert": [
      {
        "id": 21,
        "question": "Quelle actrice a porté la même robe aux Oscars 1962 et 2018 ?",
        "propositions": [
          "Barbra Streisand",
          "Rita Moreno",
          "Liza Minnelli",
          "Helen Hayes"
        ],
        "réponse": "Rita Moreno",
        "anecdote": "L'actrice culte de 'West Side Story' s'est rendue aux Oscars 2018 en portant la même robe qu'en 1962, et elle était superbe."
      },
      {
        "id": 22,
        "question": "Qui a enveloppé quelques piques à Kim Kardashian dans 'Top Off' ?",
        "propositions": [
          "Britney Spears",
          "Janet Jackson",
          "Beyoncé",
          "Nicky Minaj"
        ],
        "réponse": "Beyoncé",
        "anecdote": "La partie du titre qui fait référence à Internet vise directement la mythique photo de Kim Kardashian pour Paper Magazine."
      },
      {
        "id": 23,
        "question": "Quel comédien emblématique de la série 'Palace' s'est suicidé à 64 ans ?",
        "propositions": [
          "Georges Peyrou",
          "Bernard Pisani",
          "Olivier Pagès",
          "Marcel Philippot"
        ],
        "réponse": "Marcel Philippot",
        "anecdote": "Cette disparition fut très inattendue, d'autant qu'il travaillait ces dernières semaines sur une nouvelle pièce de théâtre."
      },
      {
        "id": 24,
        "question": "Quel journaliste de mode a décortiqué le meilleur de la Fashion Week sur TMC ?",
        "propositions": [
          "Loïc Prigent",
          "Marcel Schlutt",
          "Eric Wilson",
          "François Baudot"
        ],
        "réponse": "Loïc Prigent",
        "anecdote": "Le spécialiste de la mode propose tous les soirs sur TMC à 19h15, une sélection des meilleurs moments des défilés parisiens."
      },
      {
        "id": 25,
        "question": "Quelle jeune actrice attaque les producteurs du film 'Ghostland' ?",
        "propositions": [
          "Emilia Jones",
          "Crystal Reed",
          "Taylor Hickson",
          "Alicia Johnston"
        ],
        "réponse": "Taylor Hickson",
        "anecdote": "Taylor Hickson a été grièvement blessée sur le tournage du film d'horreur 'Ghostland', qui s'apprête à sortir en salles."
      },
      {
        "id": 26,
        "question": "Quelle actrice australienne est devenue égérie de la marque Chanel ?",
        "propositions": [
          "Margot Robbie",
          "Nicole Kidman",
          "Brittany Byrnes",
          "Kylie Watson"
        ],
        "réponse": "Margot Robbie",
        "anecdote": "Margot Robbie était une des femmes les plus en vue lors de la cérémonie des Oscars, en lice pour le prix de la Meilleure Actrice."
      },
      {
        "id": 27,
        "question": "Quelle fille de Judy Garland a été diagnostiquée d'une tumeur au cerveau ?",
        "propositions": [
          "Morgan Lily",
          "Lorna Luft",
          "Julia Ling",
          "Bianca Lawson"
        ],
        "réponse": "Lorna Luft",
        "anecdote": "Déjà victime d'un cancer du sein qui l'avait frappée il y a six ans, Lorna Luft a de nouveau été hospitalisée le 9 mars 2018."
      },
      {
        "id": 28,
        "question": "Quelle cheffe étoilée possède désormais une poupée Barbie à son effigie ?",
        "propositions": [
          "Amandine Chaignot",
          "Andrée Rosier",
          "Hélène Darroze",
          "Anne-Sophie Pic"
        ],
        "réponse": "Hélène Darroze",
        "anecdote": "Mattel rend ainsi hommage à des femmes d'excep­tion dans le monde entier à l'occa­sion de la jour­née des droits des femmes."
      },
      {
        "id": 29,
        "question": "Quelle fille d'Alexandra Lamy s'est affichée sexy sur son compte Instagram ?",
        "propositions": [
          "Priscilla Betti",
          "Mélanie Doutey",
          "Sylvie Jobert",
          "Chloé Jouannet"
        ],
        "réponse": "Chloé Jouannet",
        "anecdote": "Côté cinéma, Chloé Jouannet au tempérament frappé partageait en 2014 l'écran avec Jean Reno dans le film 'Avis de Mistral'."
      },
      {
        "id": 30,
        "question": "Qui est « la voix » qui incarne depuis longtemps la société de transport SNCF ?",
        "propositions": [
          "Élisabeth Borne",
          "Mireille Faugère",
          "Simone Herault",
          "Danièle Irazu"
        ],
        "réponse": "Simone Herault",
        "anecdote": "Simone Herault est la dame qui nous demande de nous éloigner de la bordure des quais de la SNCF qui fête cette année ses 80 ans."
      }
    ]
  }
}